{
  "sourceOfTruth": "laravel_public_api",
  "databaseQueriesFromNext": false,
  "apiBackedRoutes": [
    { "routeKey": "blog-index", "endpoint": "/v2/blog", "method": "GET" },
    { "routeKey": "blog-detail", "endpoint": "/v2/blog/{slug}", "method": "GET" },
    { "routeKey": "cms-page", "endpoint": "/v2/pages/{slug}", "method": "GET" },
    { "routeKey": "faq", "endpoint": "/v2/help/faqs", "method": "GET" },
    { "routeKey": "listings", "endpoint": "/v2/listings", "method": "GET" },
    { "routeKey": "listingDetail", "endpoint": "/v2/listings/{id}", "method": "GET" },
    { "routeKey": "events", "endpoint": "/v2/events", "method": "GET" },
    { "routeKey": "eventDetail", "endpoint": "/v2/events/{id}", "method": "GET" },
    { "routeKey": "groups", "endpoint": "/v2/groups", "method": "GET" },
    { "routeKey": "groupDetail", "endpoint": "/v2/groups/{id}", "method": "GET" },
    { "routeKey": "jobs", "endpoint": "/v2/jobs", "method": "GET" },
    { "routeKey": "jobDetail", "endpoint": "/v2/jobs/{id}", "method": "GET" },
    { "routeKey": "courses", "endpoint": "/v2/courses", "method": "GET" },
    { "routeKey": "courseDetail", "endpoint": "/v2/courses/{idOrSlug}", "method": "GET" },
    { "routeKey": "podcasts", "endpoint": "/v2/podcasts", "method": "GET" },
    { "routeKey": "podcastShow", "endpoint": "/v2/podcasts/{showSlug}", "method": "GET" },
    { "routeKey": "podcastEpisode", "endpoint": "/v2/podcasts/{showSlug}/{episodeSlug}", "method": "GET" },
    { "routeKey": "organisations", "endpoint": "/v2/volunteering/organisations", "method": "GET" },
    { "routeKey": "organisationDetail", "endpoint": "/v2/volunteering/organisations/{id}", "method": "GET" },
    { "routeKey": "resources", "endpoint": "/v2/resources", "method": "GET" },
    { "routeKey": "kb", "endpoint": "/v2/kb", "method": "GET" },
    { "routeKey": "kbDetail", "endpoint": "/v2/kb/{id}", "method": "GET" },
    { "routeKey": "marketplace", "endpoint": "/v2/marketplace/listings", "method": "GET" },
    { "routeKey": "marketplaceSearch", "endpoint": "/v2/marketplace/listings", "method": "GET" },
    { "routeKey": "marketplaceMap", "endpoint": "/v2/marketplace/listings/nearby", "method": "GET" },
    { "routeKey": "marketplaceFree", "endpoint": "/v2/marketplace/listings/free", "method": "GET" },
    { "routeKey": "marketplaceDetail", "endpoint": "/v2/marketplace/listings/{id}", "method": "GET" },
    { "routeKey": "marketplaceSeller", "endpoint": "/v2/marketplace/sellers/{id}", "method": "GET" },
    { "routeKey": "explore", "endpoint": "/v2/explore", "method": "GET" },
    { "routeKey": "volunteering", "endpoint": "/v2/volunteering/opportunities", "method": "GET" },
    { "routeKey": "volunteeringOpportunityDetail", "endpoint": "/v2/volunteering/opportunities/{id}", "method": "GET" },
    { "routeKey": "ideation", "endpoint": "/v2/ideation-challenges", "method": "GET" },
    { "routeKey": "ideationDetail", "endpoint": "/v2/ideation-challenges/{id}", "method": "GET" },
    { "routeKey": "clubs", "endpoint": "/v2/clubs", "method": "GET" }
  ]
}
